mystx-0.3.4.dist-info/METADATA
mystx-0.3.4.dist-info/WHEEL
mystx-0.3.4.dist-info/entry_points.txt
mystx-0.3.4.dist-info/licenses/LICENSE
mystx/__init__.py
mystx/config.py
mystx/ext/__init__.py
mystx/ext/github_readme_stats/__init__.py
mystx/ext/github_readme_stats/base.py
mystx/ext/github_readme_stats/pinned_repo.py
mystx/ext/github_readme_stats/stats.py
mystx/ext/github_readme_stats/top_langs.py
mystx/ext/github_readme_stats/wakatime.py
mystx/theme.py
mystx/theme/mystx/layout.html
mystx/theme/mystx/static/css/custom.css
mystx/theme/mystx/static/css/tippy.css
mystx/theme/mystx/static/css/try_examples.css
mystx/theme/mystx/static/js/custom-icon.js
mystx/theme/mystx/theme.toml
mystx/version_switcher.py
mystx-0.3.4.dist-info/RECORD
