Metadata-Version: 2.1
Name: mystx
Version: 0.3.4
Summary: mystx 主题 - 现代化 Sphinx 文档主题
Author-Email: xinetzone <735613050@qq.com>
Maintainer-Email: xinetzone <735613050@qq.com>
License:                                  Apache License
Project-URL: Repository, https://github.com/xinetzone/mystx
Project-URL: Documentation, https://mystx.readthedocs.io/
Project-URL: Issues, https://github.com/xinetzone/mystx/issues
Requires-Python: >=3.10
Provides-Extra: doc
Requires-Dist: ablog; extra == "doc"
Requires-Dist: ipywidgets; extra == "doc"
Requires-Dist: numpy; extra == "doc"
Requires-Dist: matplotlib; extra == "doc"
Requires-Dist: sphinx-comments; extra == "doc"
Requires-Dist: myst-nb; extra == "doc"
Requires-Dist: nbclient; extra == "doc"
Requires-Dist: pandas; extra == "doc"
Requires-Dist: plotly; extra == "doc"
Requires-Dist: sphinx-design; extra == "doc"
Requires-Dist: sphinx-examples; extra == "doc"
Requires-Dist: sphinx-copybutton; extra == "doc"
Requires-Dist: sphinx-contributors; extra == "doc"
Requires-Dist: sphinx-thebe; extra == "doc"
Requires-Dist: sphinxcontrib-bibtex; extra == "doc"
Requires-Dist: sphinxext-opengraph; extra == "doc"
Requires-Dist: sphinx-sitemap; extra == "doc"
Requires-Dist: sphinx-autoapi>=3.4; extra == "doc"
Requires-Dist: graphviz; extra == "doc"
Requires-Dist: sphinx-tippy; extra == "doc"
Requires-Dist: sphinx-pyscript; extra == "doc"
Provides-Extra: dev
Requires-Dist: taolib; extra == "dev"
Requires-Dist: invoke; extra == "dev"
Requires-Dist: sphinx-book-theme; extra == "dev"
Requires-Dist: sphinx; extra == "dev"
Requires-Dist: myst-nb; extra == "dev"
Requires-Dist: myst-parser; extra == "dev"
Requires-Dist: myst-docutils>=4.0; extra == "dev"
Requires-Dist: docutils>=0.20; extra == "dev"
